<?xml version="1.0" encoding="gb2312" ?><?xml-stylesheet type="text/xsl" href="D:\Program Files\National Instruments\TestStand 2014\Components\Models\TestStandModels\ATML\StyleSheets\tr5_horizontal.xsl"?>

<trc:TestResultsCollection xmlns:trc="urn:IEEE-1636.1:2011:01:TestResultsCollection" xmlns:tr="urn:IEEE-1636.1:2011:01:TestResults" xmlns:c="urn:IEEE-1671:2010:Common" xmlns:xsi="http://www.w3.org/2001/XMLSchema-instance" xmlns:ts="www.ni.com/TestStand/ATMLTestResults/2.0">
<trc:TestResults uuid="0dd2ce55-cf55-4740-80d7-842d1711a11c" xmlns:trc="urn:IEEE-1636.1:2011:01:TestResultsCollection" xmlns:tr="urn:IEEE-1636.1:2011:01:TestResults" xmlns:c="urn:IEEE-1671:2010:Common" xmlns:xsi="http://www.w3.org/2001/XMLSchema-instance" xmlns:ts="www.ni.com/TestStand/ATMLTestResults/2.0">
	<tr:Personnel>
		<tr:SystemOperator ID = "administrator" name = "administrator"/>
	</tr:Personnel>
	<tr:ResultSet ID="4" name = "F:\Bluewave New Energy\SVN_Work\AutoTest_TestStand\trunk\AutoTest_TestStand\SEQ\BCU CalibrateVoltTest.seq#MainSequence" startDateTime = "2016-03-19T10:01:09.142" endDateTime = "2016-03-19T10:02:22.651">
		<tr:Extension>
			<ts:TSStepProperties>
				<ts:StepType>SequenceCall</ts:StepType>
				<ts:StepGroup>Main</ts:StepGroup>
				<ts:BlockLevel value='1'/>
				<ts:Index value='9'/>
				<ts:TotalTime value='73.5092'/>
				<ts:ModuleTime value='73.5088'/>
			</ts:TSStepProperties>
		</tr:Extension>
		<tr:Outcome value="Aborted" qualifier="Terminated" />
		<tr:SessionAction ID = "6" name = "OpenPort" startDateTime = "2016-03-19T10:01:09.273"  endDateTime = "2016-03-19T10:01:09.337"  testReferenceID="ID#:tq2JndjBLEOmXNX+o0D0/B">
			<tr:Extension>
				<ts:TSStepProperties>
					<ts:StepType>Action</ts:StepType>
					<ts:StepGroup>Setup</ts:StepGroup>
					<ts:BlockLevel value='0'/>
					<ts:Index value='0'/>
					<ts:TotalTime value='0.0642053'/>
					<ts:ModuleTime value='0.0633623'/>
				</ts:TSStepProperties>
			</tr:Extension>
			<tr:ActionOutcome value = "Done" />
		</tr:SessionAction>
		<tr:SessionAction ID = "8" name = "ZlgCan_Open_BATH" startDateTime = "2016-03-19T10:01:09.352"  endDateTime = "2016-03-19T10:01:09.449"  testReferenceID="ID#:lbxYZw3tFEmvvshsHysnLA">
			<tr:Extension>
				<ts:TSStepProperties>
					<ts:StepType>Action</ts:StepType>
					<ts:StepGroup>Setup</ts:StepGroup>
					<ts:BlockLevel value='0'/>
					<ts:Index value='1'/>
					<ts:TotalTime value='0.0968461'/>
					<ts:ModuleTime value='0.0966165'/>
				</ts:TSStepProperties>
			</tr:Extension>
			<tr:ActionOutcome value = "Done" />
		</tr:SessionAction>
		<tr:SessionAction ID = "9" name = "Set curr 10ma" startDateTime = "2016-03-19T10:01:09.455"  endDateTime = "2016-03-19T10:01:09.496"  testReferenceID="ID#:UR2kP0SZME6uFr/Q6yg2AA">
			<tr:Extension>
				<ts:TSStepProperties>
					<ts:StepType>Action</ts:StepType>
					<ts:StepGroup>Main</ts:StepGroup>
					<ts:BlockLevel value='0'/>
					<ts:Index value='0'/>
					<ts:TotalTime value='0.0417543'/>
					<ts:ModuleTime value='0.0415327'/>
				</ts:TSStepProperties>
			</tr:Extension>
			<tr:ActionOutcome value = "Done" />
		</tr:SessionAction>
		<tr:SessionAction ID = "10" name = "OutPutOn" startDateTime = "2016-03-19T10:01:09.498"  endDateTime = "2016-03-19T10:01:09.540"  testReferenceID="ID#:7EeGvqmbg0Cd3ocqqghngD">
			<tr:Extension>
				<ts:TSStepProperties>
					<ts:StepType>Action</ts:StepType>
					<ts:StepGroup>Main</ts:StepGroup>
					<ts:BlockLevel value='0'/>
					<ts:Index value='1'/>
					<ts:TotalTime value='0.042462'/>
					<ts:ModuleTime value='0.0422572'/>
				</ts:TSStepProperties>
			</tr:Extension>
			<tr:ActionOutcome value = "Done" />
		</tr:SessionAction>
		<tr:Test ID = "11" name = "Set Volt 200V" startDateTime = "2016-03-19T10:01:09.542"  endDateTime = "2016-03-19T10:01:09.542"  testReferenceID="ID#:0Z0JzXGxS0+l6pT3tfTb0C">
			<tr:Extension>
				<ts:TSStepProperties>
					<ts:StepType>Action</ts:StepType>
					<ts:StepGroup>Main</ts:StepGroup>
					<ts:BlockLevel value='0'/>
					<ts:Index value='2'/>
					<ts:TotalTime value='1.26e-005'/>
				</ts:TSStepProperties>
			</tr:Extension>
			<tr:Outcome value = "UserDefined" qualifier= "Skipped" />
		</tr:Test>
		<tr:Test ID = "12" name = "Wait" startDateTime = "2016-03-19T10:01:09.544"  endDateTime = "2016-03-19T10:01:09.544"  testReferenceID="ID#:CcBxrSEb90W4efJppVmu1D">
			<tr:Extension>
				<ts:TSStepProperties>
					<ts:StepType>NI_Wait</ts:StepType>
					<ts:StepGroup>Main</ts:StepGroup>
					<ts:BlockLevel value='0'/>
					<ts:Index value='3'/>
					<ts:TotalTime value='2.19e-005'/>
				</ts:TSStepProperties>
			</tr:Extension>
			<tr:Outcome value = "UserDefined" qualifier= "Skipped" />
		</tr:Test>
		<tr:Test ID = "13" name = "GetInSumvAD1" startDateTime = "2016-03-19T10:01:09.547"  endDateTime = "2016-03-19T10:01:09.547"  testReferenceID="ID#:2UULFOXpLUW1mGy0mCD63A">
			<tr:Extension>
				<ts:TSStepProperties>
					<ts:StepType>Action</ts:StepType>
					<ts:StepGroup>Main</ts:StepGroup>
					<ts:BlockLevel value='0'/>
					<ts:Index value='4'/>
					<ts:TotalTime value='1.31e-005'/>
				</ts:TSStepProperties>
			</tr:Extension>
			<tr:Outcome value = "UserDefined" qualifier= "Skipped" />
		</tr:Test>
		<tr:Test ID = "14" name = "Wait" startDateTime = "2016-03-19T10:01:09.549"  endDateTime = "2016-03-19T10:01:09.549"  testReferenceID="ID#:dnib2JXUNE2M44LKWgXaUB">
			<tr:Extension>
				<ts:TSStepProperties>
					<ts:StepType>NI_Wait</ts:StepType>
					<ts:StepGroup>Main</ts:StepGroup>
					<ts:BlockLevel value='0'/>
					<ts:Index value='5'/>
					<ts:TotalTime value='1.17e-005'/>
				</ts:TSStepProperties>
			</tr:Extension>
			<tr:Outcome value = "UserDefined" qualifier= "Skipped" />
		</tr:Test>
		<tr:Test ID = "15" name = "Set Volt 400V" startDateTime = "2016-03-19T10:01:09.553"  endDateTime = "2016-03-19T10:01:09.553"  testReferenceID="ID#:EIG5EVmWn0yQbYENK0HuBC">
			<tr:Extension>
				<ts:TSStepProperties>
					<ts:StepType>Action</ts:StepType>
					<ts:StepGroup>Main</ts:StepGroup>
					<ts:BlockLevel value='0'/>
					<ts:Index value='6'/>
					<ts:TotalTime value='1.45e-005'/>
				</ts:TSStepProperties>
			</tr:Extension>
			<tr:Outcome value = "UserDefined" qualifier= "Skipped" />
		</tr:Test>
		<tr:Test ID = "16" name = "Wait" startDateTime = "2016-03-19T10:01:09.557"  endDateTime = "2016-03-19T10:01:09.557"  testReferenceID="ID#:tmCHvkcTrka7edZveLerID">
			<tr:Extension>
				<ts:TSStepProperties>
					<ts:StepType>NI_Wait</ts:StepType>
					<ts:StepGroup>Main</ts:StepGroup>
					<ts:BlockLevel value='0'/>
					<ts:Index value='7'/>
					<ts:TotalTime value='1.26e-005'/>
				</ts:TSStepProperties>
			</tr:Extension>
			<tr:Outcome value = "UserDefined" qualifier= "Skipped" />
		</tr:Test>
		<tr:Test ID = "17" name = "GetInSumvAD2" startDateTime = "2016-03-19T10:01:09.560"  endDateTime = "2016-03-19T10:01:09.560"  testReferenceID="ID#:WjR0UygYA0aA9H5bvLg5CB">
			<tr:Extension>
				<ts:TSStepProperties>
					<ts:StepType>Action</ts:StepType>
					<ts:StepGroup>Main</ts:StepGroup>
					<ts:BlockLevel value='0'/>
					<ts:Index value='8'/>
					<ts:TotalTime value='3.17e-005'/>
				</ts:TSStepProperties>
			</tr:Extension>
			<tr:Outcome value = "UserDefined" qualifier= "Skipped" />
		</tr:Test>
		<tr:Test ID = "18" name = "CalInSumV" startDateTime = "2016-03-19T10:01:09.564"  endDateTime = "2016-03-19T10:01:09.564"  testReferenceID="ID#:7vXQmMdc5ki/CUoRiJmUTD">
			<tr:Extension>
				<ts:TSStepProperties>
					<ts:StepType>Action</ts:StepType>
					<ts:StepGroup>Main</ts:StepGroup>
					<ts:BlockLevel value='0'/>
					<ts:Index value='9'/>
					<ts:TotalTime value='1.4e-005'/>
				</ts:TSStepProperties>
			</tr:Extension>
			<tr:Outcome value = "UserDefined" qualifier= "Skipped" />
		</tr:Test>
		<tr:Test ID = "19" name = "Wait" startDateTime = "2016-03-19T10:01:09.567"  endDateTime = "2016-03-19T10:01:09.567"  testReferenceID="ID#:WJck2Rx4gEu0zg+FCl0EcD">
			<tr:Extension>
				<ts:TSStepProperties>
					<ts:StepType>NI_Wait</ts:StepType>
					<ts:StepGroup>Main</ts:StepGroup>
					<ts:BlockLevel value='0'/>
					<ts:Index value='10'/>
					<ts:TotalTime value='3.31e-005'/>
				</ts:TSStepProperties>
			</tr:Extension>
			<tr:Outcome value = "UserDefined" qualifier= "Skipped" />
		</tr:Test>
		<tr:Test ID = "20" name = "Set Volt 20V" startDateTime = "2016-03-19T10:01:09.571"  endDateTime = "2016-03-19T10:01:09.571"  testReferenceID="ID#:+QhGL7Czt06xbYlV7AdsBD">
			<tr:Extension>
				<ts:TSStepProperties>
					<ts:StepType>Action</ts:StepType>
					<ts:StepGroup>Main</ts:StepGroup>
					<ts:BlockLevel value='0'/>
					<ts:Index value='11'/>
					<ts:TotalTime value='5.09e-005'/>
				</ts:TSStepProperties>
			</tr:Extension>
			<tr:Outcome value = "UserDefined" qualifier= "Skipped" />
		</tr:Test>
		<tr:Test ID = "21" name = "Wait" startDateTime = "2016-03-19T10:01:09.575"  endDateTime = "2016-03-19T10:01:09.575"  testReferenceID="ID#:0BZY0JTd0kCsQVZAXXu7jD">
			<tr:Extension>
				<ts:TSStepProperties>
					<ts:StepType>NI_Wait</ts:StepType>
					<ts:StepGroup>Main</ts:StepGroup>
					<ts:BlockLevel value='0'/>
					<ts:Index value='12'/>
					<ts:TotalTime value='1.4e-005'/>
				</ts:TSStepProperties>
			</tr:Extension>
			<tr:Outcome value = "UserDefined" qualifier= "Skipped" />
		</tr:Test>
		<tr:Test ID = "22" name = "BHN01_BCU_20V_内部电压精度测试" startDateTime = "2016-03-19T10:01:09.577"  endDateTime = "2016-03-19T10:01:09.577"  testReferenceID="ID#:eO50KHkO0kyjEAt/gKZcpD">
			<tr:Extension>
				<ts:TSStepProperties>
					<ts:StepType>NI_MultipleNumericLimitTest</ts:StepType>
					<ts:StepGroup>Main</ts:StepGroup>
					<ts:BlockLevel value='0'/>
					<ts:Index value='13'/>
					<ts:LoopingProperties>
						<ts:NumLoops value='0' xsi:type='c:double'/>
						<ts:NumPassed value='0' xsi:type='c:double'/>
						<ts:NumFailed value='0' xsi:type='c:double'/>
						<ts:EndingLoopIndex value='0' xsi:type='c:double'/>
					</ts:LoopingProperties>
					<ts:TotalTime value='1.63e-005'/>
				</ts:TSStepProperties>
			</tr:Extension>
			<tr:Outcome value = "UserDefined" qualifier= "Skipped" />
		</tr:Test>
		<tr:Test ID = "23" name = "Set Volt 80V" startDateTime = "2016-03-19T10:01:09.581"  endDateTime = "2016-03-19T10:01:09.581"  testReferenceID="ID#:zfDflhZyEUSLvicqCaxlhC">
			<tr:Extension>
				<ts:TSStepProperties>
					<ts:StepType>Action</ts:StepType>
					<ts:StepGroup>Main</ts:StepGroup>
					<ts:BlockLevel value='0'/>
					<ts:Index value='14'/>
					<ts:TotalTime value='1.54e-005'/>
				</ts:TSStepProperties>
			</tr:Extension>
			<tr:Outcome value = "UserDefined" qualifier= "Skipped" />
		</tr:Test>
		<tr:Test ID = "24" name = "Wait" startDateTime = "2016-03-19T10:01:09.583"  endDateTime = "2016-03-19T10:01:09.583"  testReferenceID="ID#:lM0mN0f1MEWpEF0irB4cUD">
			<tr:Extension>
				<ts:TSStepProperties>
					<ts:StepType>NI_Wait</ts:StepType>
					<ts:StepGroup>Main</ts:StepGroup>
					<ts:BlockLevel value='0'/>
					<ts:Index value='15'/>
					<ts:TotalTime value='1.26e-005'/>
				</ts:TSStepProperties>
			</tr:Extension>
			<tr:Outcome value = "UserDefined" qualifier= "Skipped" />
		</tr:Test>
		<tr:Test ID = "25" name = "BHN01_BCU_80V_内部电压精度测试" startDateTime = "2016-03-19T10:01:09.588"  endDateTime = "2016-03-19T10:01:09.588"  testReferenceID="ID#:XlCYn7kGGU+Gr/QBw4B02C">
			<tr:Extension>
				<ts:TSStepProperties>
					<ts:StepType>NI_MultipleNumericLimitTest</ts:StepType>
					<ts:StepGroup>Main</ts:StepGroup>
					<ts:BlockLevel value='0'/>
					<ts:Index value='16'/>
					<ts:LoopingProperties>
						<ts:NumLoops value='0' xsi:type='c:double'/>
						<ts:NumPassed value='0' xsi:type='c:double'/>
						<ts:NumFailed value='0' xsi:type='c:double'/>
						<ts:EndingLoopIndex value='0' xsi:type='c:double'/>
					</ts:LoopingProperties>
					<ts:TotalTime value='5.13e-005'/>
				</ts:TSStepProperties>
			</tr:Extension>
			<tr:Outcome value = "UserDefined" qualifier= "Skipped" />
		</tr:Test>
		<tr:Test ID = "26" name = "Set Volt 190V" startDateTime = "2016-03-19T10:01:09.591"  endDateTime = "2016-03-19T10:01:09.591"  testReferenceID="ID#:bc4YHqsU3kKUzu0R/5VMqC">
			<tr:Extension>
				<ts:TSStepProperties>
					<ts:StepType>Action</ts:StepType>
					<ts:StepGroup>Main</ts:StepGroup>
					<ts:BlockLevel value='0'/>
					<ts:Index value='17'/>
					<ts:TotalTime value='2.1e-005'/>
				</ts:TSStepProperties>
			</tr:Extension>
			<tr:Outcome value = "UserDefined" qualifier= "Skipped" />
		</tr:Test>
		<tr:Test ID = "27" name = "Wait" startDateTime = "2016-03-19T10:01:09.594"  endDateTime = "2016-03-19T10:01:09.594"  testReferenceID="ID#:L5SiZhvtRkKNbU7scm00BC">
			<tr:Extension>
				<ts:TSStepProperties>
					<ts:StepType>NI_Wait</ts:StepType>
					<ts:StepGroup>Main</ts:StepGroup>
					<ts:BlockLevel value='0'/>
					<ts:Index value='18'/>
					<ts:TotalTime value='1.63e-005'/>
				</ts:TSStepProperties>
			</tr:Extension>
			<tr:Outcome value = "UserDefined" qualifier= "Skipped" />
		</tr:Test>
		<tr:Test ID = "28" name = "BHN01_BCU_190V_内部电压精度测试" startDateTime = "2016-03-19T10:01:09.598"  endDateTime = "2016-03-19T10:01:09.598"  testReferenceID="ID#:9OhbdasMZUSgfyGOyfB3LD">
			<tr:Extension>
				<ts:TSStepProperties>
					<ts:StepType>NI_MultipleNumericLimitTest</ts:StepType>
					<ts:StepGroup>Main</ts:StepGroup>
					<ts:BlockLevel value='0'/>
					<ts:Index value='19'/>
					<ts:LoopingProperties>
						<ts:NumLoops value='0' xsi:type='c:double'/>
						<ts:NumPassed value='0' xsi:type='c:double'/>
						<ts:NumFailed value='0' xsi:type='c:double'/>
						<ts:EndingLoopIndex value='0' xsi:type='c:double'/>
					</ts:LoopingProperties>
					<ts:TotalTime value='2.61e-005'/>
				</ts:TSStepProperties>
			</tr:Extension>
			<tr:Outcome value = "UserDefined" qualifier= "Skipped" />
		</tr:Test>
		<tr:Test ID = "29" name = "Set Volt 390V" startDateTime = "2016-03-19T10:01:09.601"  endDateTime = "2016-03-19T10:01:09.601"  testReferenceID="ID#:0ck/enNjpU+bzvrfm4i1sB">
			<tr:Extension>
				<ts:TSStepProperties>
					<ts:StepType>Action</ts:StepType>
					<ts:StepGroup>Main</ts:StepGroup>
					<ts:BlockLevel value='0'/>
					<ts:Index value='20'/>
					<ts:TotalTime value='1.45e-005'/>
				</ts:TSStepProperties>
			</tr:Extension>
			<tr:Outcome value = "UserDefined" qualifier= "Skipped" />
		</tr:Test>
		<tr:Test ID = "30" name = "Wait" startDateTime = "2016-03-19T10:01:09.604"  endDateTime = "2016-03-19T10:01:09.604"  testReferenceID="ID#:c9EHX9qfV0mRUNq9uXxdJC">
			<tr:Extension>
				<ts:TSStepProperties>
					<ts:StepType>NI_Wait</ts:StepType>
					<ts:StepGroup>Main</ts:StepGroup>
					<ts:BlockLevel value='0'/>
					<ts:Index value='21'/>
					<ts:TotalTime value='1.35e-005'/>
				</ts:TSStepProperties>
			</tr:Extension>
			<tr:Outcome value = "UserDefined" qualifier= "Skipped" />
		</tr:Test>
		<tr:Test ID = "31" name = "BHN01_BCU_390V_内部电压精度测试" startDateTime = "2016-03-19T10:01:09.607"  endDateTime = "2016-03-19T10:01:09.607"  testReferenceID="ID#:Qi70JUu0b06l1UiYupcWXC">
			<tr:Extension>
				<ts:TSStepProperties>
					<ts:StepType>NI_MultipleNumericLimitTest</ts:StepType>
					<ts:StepGroup>Main</ts:StepGroup>
					<ts:BlockLevel value='0'/>
					<ts:Index value='22'/>
					<ts:LoopingProperties>
						<ts:NumLoops value='0' xsi:type='c:double'/>
						<ts:NumPassed value='0' xsi:type='c:double'/>
						<ts:NumFailed value='0' xsi:type='c:double'/>
						<ts:EndingLoopIndex value='0' xsi:type='c:double'/>
					</ts:LoopingProperties>
					<ts:TotalTime value='0.0001801'/>
				</ts:TSStepProperties>
			</tr:Extension>
			<tr:Outcome value = "UserDefined" qualifier= "Skipped" />
		</tr:Test>
		<tr:Test ID = "32" name = "Set Volt 800V" startDateTime = "2016-03-19T10:01:09.612"  endDateTime = "2016-03-19T10:01:09.612"  testReferenceID="ID#:YUg6wI9iIU205rtPwY6yjA">
			<tr:Extension>
				<ts:TSStepProperties>
					<ts:StepType>Action</ts:StepType>
					<ts:StepGroup>Main</ts:StepGroup>
					<ts:BlockLevel value='0'/>
					<ts:Index value='23'/>
					<ts:TotalTime value='1.87e-005'/>
				</ts:TSStepProperties>
			</tr:Extension>
			<tr:Outcome value = "UserDefined" qualifier= "Skipped" />
		</tr:Test>
		<tr:Test ID = "33" name = "Wait" startDateTime = "2016-03-19T10:01:09.615"  endDateTime = "2016-03-19T10:01:09.615"  testReferenceID="ID#:y5PoRcdSQ0iUt/qltroVyA">
			<tr:Extension>
				<ts:TSStepProperties>
					<ts:StepType>NI_Wait</ts:StepType>
					<ts:StepGroup>Main</ts:StepGroup>
					<ts:BlockLevel value='0'/>
					<ts:Index value='24'/>
					<ts:TotalTime value='1.26e-005'/>
				</ts:TSStepProperties>
			</tr:Extension>
			<tr:Outcome value = "UserDefined" qualifier= "Skipped" />
		</tr:Test>
		<tr:Test ID = "34" name = "BHN01_BCU_800V_内部电压精度测试" startDateTime = "2016-03-19T10:01:09.618"  endDateTime = "2016-03-19T10:01:09.618"  testReferenceID="ID#:p6k3aEMda0qo40rRU7jt3A">
			<tr:Extension>
				<ts:TSStepProperties>
					<ts:StepType>NI_MultipleNumericLimitTest</ts:StepType>
					<ts:StepGroup>Main</ts:StepGroup>
					<ts:BlockLevel value='0'/>
					<ts:Index value='25'/>
					<ts:LoopingProperties>
						<ts:NumLoops value='0' xsi:type='c:double'/>
						<ts:NumPassed value='0' xsi:type='c:double'/>
						<ts:NumFailed value='0' xsi:type='c:double'/>
						<ts:EndingLoopIndex value='0' xsi:type='c:double'/>
					</ts:LoopingProperties>
					<ts:TotalTime value='1.82e-005'/>
				</ts:TSStepProperties>
			</tr:Extension>
			<tr:Outcome value = "UserDefined" qualifier= "Skipped" />
		</tr:Test>
		<tr:SessionAction ID = "35" name = "Wait" startDateTime = "2016-03-19T10:01:09.626"  endDateTime = "2016-03-19T10:01:12.633"  testReferenceID="ID#:YP41ZaoICkyqAFeZkDVPNB">
			<tr:Extension>
				<ts:TSStepProperties>
					<ts:StepType>NI_Wait</ts:StepType>
					<ts:StepGroup>Main</ts:StepGroup>
					<ts:BlockLevel value='0'/>
					<ts:Index value='27'/>
					<ts:TotalTime value='3.00636'/>
				</ts:TSStepProperties>
			</tr:Extension>
			<tr:ActionOutcome value = "Done" />
		</tr:SessionAction>
		<tr:SessionAction ID = "37" name = "Set Volt 200V" startDateTime = "2016-03-19T10:01:12.649"  endDateTime = "2016-03-19T10:01:12.753"  testReferenceID="ID#:TlanYw5BDketFAYau+neLB">
			<tr:Extension>
				<ts:TSStepProperties>
					<ts:StepType>Action</ts:StepType>
					<ts:StepGroup>Main</ts:StepGroup>
					<ts:BlockLevel value='0'/>
					<ts:Index value='28'/>
					<ts:TotalTime value='0.103996'/>
					<ts:ModuleTime value='0.103202'/>
				</ts:TSStepProperties>
			</tr:Extension>
			<tr:ActionOutcome value = "Done" />
		</tr:SessionAction>
		<tr:SessionAction ID = "38" name = "Wait" startDateTime = "2016-03-19T10:01:12.757"  endDateTime = "2016-03-19T10:01:15.757"  testReferenceID="ID#:7hSUizVpEkeNOaTTjTeg4A">
			<tr:Extension>
				<ts:TSStepProperties>
					<ts:StepType>NI_Wait</ts:StepType>
					<ts:StepGroup>Main</ts:StepGroup>
					<ts:BlockLevel value='0'/>
					<ts:Index value='29'/>
					<ts:TotalTime value='3.00028'/>
				</ts:TSStepProperties>
			</tr:Extension>
			<tr:ActionOutcome value = "Done" />
		</tr:SessionAction>
		<tr:SessionAction ID = "40" name = "GetOutSumvAD1" startDateTime = "2016-03-19T10:01:15.767"  endDateTime = "2016-03-19T10:01:23.828"  testReferenceID="ID#:gHuDbyaHl0Sz7tBkJvMvOC">
			<tr:Data>
				<c:Collection>
					<c:Item name = "Data">
						<c:IndexedArray dimensions="[0]" lowerBounds="[0]" upperBounds="[]" xsi:type="ts:TS_doubleArray" flags = "0x2000">
						</c:IndexedArray>
					</c:Item>
					<c:Item name = "Value">
						<c:Datum value = "0" xsi:type="ts:TS_unsignedLong" flags = "0x2000"/>
					</c:Item>
				</c:Collection>
			</tr:Data>
			<tr:Extension>
				<ts:TSStepProperties>
					<ts:StepType>Action</ts:StepType>
					<ts:StepGroup>Main</ts:StepGroup>
					<ts:BlockLevel value='0'/>
					<ts:Index value='30'/>
					<ts:TotalTime value='8.06092'/>
					<ts:ModuleTime value='8.06075'/>
				</ts:TSStepProperties>
			</tr:Extension>
			<tr:ActionOutcome value = "Done" />
		</tr:SessionAction>
		<tr:SessionAction ID = "41" name = "Wait" startDateTime = "2016-03-19T10:01:23.830"  endDateTime = "2016-03-19T10:01:24.830"  testReferenceID="ID#:1z2zG7SZY0G1K7vUkm/pGA">
			<tr:Extension>
				<ts:TSStepProperties>
					<ts:StepType>NI_Wait</ts:StepType>
					<ts:StepGroup>Main</ts:StepGroup>
					<ts:BlockLevel value='0'/>
					<ts:Index value='31'/>
					<ts:TotalTime value='1.00018'/>
				</ts:TSStepProperties>
			</tr:Extension>
			<tr:ActionOutcome value = "Done" />
		</tr:SessionAction>
		<tr:SessionAction ID = "42" name = "Set Volt 400V" startDateTime = "2016-03-19T10:01:24.832"  endDateTime = "2016-03-19T10:01:24.933"  testReferenceID="ID#:osFWLGwgQ0S3MfiN/Yck/A">
			<tr:Extension>
				<ts:TSStepProperties>
					<ts:StepType>Action</ts:StepType>
					<ts:StepGroup>Main</ts:StepGroup>
					<ts:BlockLevel value='0'/>
					<ts:Index value='32'/>
					<ts:TotalTime value='0.101375'/>
					<ts:ModuleTime value='0.101209'/>
				</ts:TSStepProperties>
			</tr:Extension>
			<tr:ActionOutcome value = "Done" />
		</tr:SessionAction>
		<tr:SessionAction ID = "43" name = "Wait" startDateTime = "2016-03-19T10:01:24.935"  endDateTime = "2016-03-19T10:01:27.935"  testReferenceID="ID#:9Ad+unrF+EWhityPQMxktC">
			<tr:Extension>
				<ts:TSStepProperties>
					<ts:StepType>NI_Wait</ts:StepType>
					<ts:StepGroup>Main</ts:StepGroup>
					<ts:BlockLevel value='0'/>
					<ts:Index value='33'/>
					<ts:TotalTime value='3.00018'/>
				</ts:TSStepProperties>
			</tr:Extension>
			<tr:ActionOutcome value = "Done" />
		</tr:SessionAction>
		<tr:SessionAction ID = "45" name = "GetOutSumvAD2" startDateTime = "2016-03-19T10:01:27.946"  endDateTime = "2016-03-19T10:01:35.991"  testReferenceID="ID#:Lrvvxj6D+EKVT52lmv4WuD">
			<tr:Data>
				<c:Collection>
					<c:Item name = "Data">
						<c:IndexedArray dimensions="[0]" lowerBounds="[0]" upperBounds="[]" xsi:type="ts:TS_doubleArray" flags = "0x2000">
						</c:IndexedArray>
					</c:Item>
					<c:Item name = "Value">
						<c:Datum value = "0" xsi:type="ts:TS_unsignedLong" flags = "0x2000"/>
					</c:Item>
				</c:Collection>
			</tr:Data>
			<tr:Extension>
				<ts:TSStepProperties>
					<ts:StepType>Action</ts:StepType>
					<ts:StepGroup>Main</ts:StepGroup>
					<ts:BlockLevel value='0'/>
					<ts:Index value='34'/>
					<ts:TotalTime value='8.04501'/>
					<ts:ModuleTime value='8.04478'/>
				</ts:TSStepProperties>
			</tr:Extension>
			<tr:ActionOutcome value = "Done" />
		</tr:SessionAction>
		<tr:SessionAction ID = "46" name = "CalOutSumV" startDateTime = "2016-03-19T10:01:35.993"  endDateTime = "2016-03-19T10:01:35.995"  testReferenceID="ID#:ik7T551J+0i6jx7jNFV9nA">
			<tr:Data>
				<c:Collection>
					<c:Item name = "Gain">
						<c:Datum xsi:type="ts:TS_string" flags = "0x2000"><c:Value>INF</c:Value></c:Datum>
					</c:Item>
					<c:Item name = "Offset">
						<c:Datum value = "2147483647" xsi:type="ts:TS_double" flags = "0x2000"/>
					</c:Item>
				</c:Collection>
			</tr:Data>
			<tr:Extension>
				<ts:TSStepProperties>
					<ts:StepType>Action</ts:StepType>
					<ts:StepGroup>Main</ts:StepGroup>
					<ts:BlockLevel value='0'/>
					<ts:Index value='35'/>
					<ts:TotalTime value='0.0021544'/>
					<ts:ModuleTime value='0.0019888'/>
				</ts:TSStepProperties>
			</tr:Extension>
			<tr:ActionOutcome value = "Done" />
		</tr:SessionAction>
		<tr:SessionAction ID = "47" name = "Wait" startDateTime = "2016-03-19T10:01:35.996"  endDateTime = "2016-03-19T10:01:37.996"  testReferenceID="ID#:GX2SLp0ViUaAfLo5a09k4B">
			<tr:Extension>
				<ts:TSStepProperties>
					<ts:StepType>NI_Wait</ts:StepType>
					<ts:StepGroup>Main</ts:StepGroup>
					<ts:BlockLevel value='0'/>
					<ts:Index value='36'/>
					<ts:TotalTime value='2.00019'/>
				</ts:TSStepProperties>
			</tr:Extension>
			<tr:ActionOutcome value = "Done" />
		</tr:SessionAction>
		<tr:SessionAction ID = "49" name = "Set Volt 20V" startDateTime = "2016-03-19T10:01:38.006"  endDateTime = "2016-03-19T10:01:38.108"  testReferenceID="ID#:uhUDDM0qDE+oQDwrl+jPUD">
			<tr:Extension>
				<ts:TSStepProperties>
					<ts:StepType>Action</ts:StepType>
					<ts:StepGroup>Main</ts:StepGroup>
					<ts:BlockLevel value='0'/>
					<ts:Index value='37'/>
					<ts:TotalTime value='0.101195'/>
					<ts:ModuleTime value='0.101015'/>
				</ts:TSStepProperties>
			</tr:Extension>
			<tr:ActionOutcome value = "Done" />
		</tr:SessionAction>
		<tr:SessionAction ID = "50" name = "Wait" startDateTime = "2016-03-19T10:01:38.109"  endDateTime = "2016-03-19T10:01:46.111"  testReferenceID="ID#:sJCTTRuLlUO7xl74YcjUQC">
			<tr:Extension>
				<ts:TSStepProperties>
					<ts:StepType>NI_Wait</ts:StepType>
					<ts:StepGroup>Main</ts:StepGroup>
					<ts:BlockLevel value='0'/>
					<ts:Index value='38'/>
					<ts:TotalTime value='8.00266'/>
				</ts:TSStepProperties>
			</tr:Extension>
			<tr:ActionOutcome value = "Done" />
		</tr:SessionAction>
		<tr:Test ID = "52" name = "BHN01_BCU_20V_外部电压精度测试" startDateTime = "2016-03-19T10:01:46.121"  endDateTime = "2016-03-19T10:02:22.487"  testReferenceID="ID#:UnY5ucYKy0+mUDRlRc0ZCC">
			<tr:Extension>
				<ts:TSStepProperties>
					<ts:StepType>NI_MultipleNumericLimitTest</ts:StepType>
					<ts:StepGroup>Main</ts:StepGroup>
					<ts:BlockLevel value='0'/>
					<ts:StepCausedSequenceFailure value='true'/>
					<ts:Index value='39'/>
					<ts:LoopingProperties>
						<ts:NumLoops value='12' xsi:type='c:double'/>
						<ts:NumPassed value='0' xsi:type='c:double'/>
						<ts:NumFailed value='12' xsi:type='c:double'/>
						<ts:EndingLoopIndex value='12' xsi:type='c:double'/>
					</ts:LoopingProperties>
					<ts:TotalTime value='36.3658'/>
					<ts:ModuleTime value='36.2657'/>
				</ts:TSStepProperties>
			</tr:Extension>
			<tr:Outcome value = "Aborted" qualifier= "Terminated" />
			<tr:TestResult ID = "tr-9e0aa8b6-ed76-11e5-ba55-68f728e06079" name = "InSumv_20V">
				<tr:TestData>
					<c:Datum value = "0" xsi:type="ts:TS_double" flags = "0x0400"/>
				</tr:TestData>
				<tr:TestLimits>
					<tr:Limits>
						<c:LimitPair operator = "AND">
							<c:Limit comparator = "GE">
								<c:Datum value = "19" xsi:type="ts:TS_double" flags = "0x0000"/>
							</c:Limit>
							<c:Limit comparator = "LE">
								<c:Datum value = "20" xsi:type="ts:TS_double" flags = "0x0000"/>
							</c:Limit>
						</c:LimitPair>
					</tr:Limits>
				</tr:TestLimits>
				<tr:Outcome value = "Failed" />
			</tr:TestResult>
		</tr:Test>
		<tr:SessionAction ID = "53" name = "OutPutOFF" startDateTime = "2016-03-19T10:02:22.487"  endDateTime = "2016-03-19T10:02:22.530"  testReferenceID="ID#:NgwS9ATCT0K0tlnzbW0WUB">
			<tr:Extension>
				<ts:TSStepProperties>
					<ts:StepType>Action</ts:StepType>
					<ts:StepGroup>Cleanup</ts:StepGroup>
					<ts:BlockLevel value='0'/>
					<ts:Index value='0'/>
					<ts:TotalTime value='0.0427816'/>
					<ts:ModuleTime value='0.0425633'/>
				</ts:TSStepProperties>
			</tr:Extension>
			<tr:ActionOutcome value = "Done" />
		</tr:SessionAction>
		<tr:Test ID = "54" name = "ZlgCan_Close_BATH" startDateTime = "2016-03-19T10:02:22.530"  endDateTime = "2016-03-19T10:02:22.632"  testReferenceID="ID#:f0YCyZi2FUGPSD6qysvWeA">
			<tr:Extension>
				<ts:TSStepProperties>
					<ts:StepType>Action</ts:StepType>
					<ts:StepGroup>Cleanup</ts:StepGroup>
					<ts:BlockLevel value='0'/>
					<ts:Index value='1'/>
					<ts:TotalTime value='0.101965'/>
					<ts:ModuleTime value='0.101741'/>
				</ts:TSStepProperties>
			</tr:Extension>
			<tr:Outcome value = "Aborted" qualifier= "Terminated" />
		</tr:Test>
		<tr:SessionAction ID = "55" name = "ClosePort" startDateTime = "2016-03-19T10:02:22.632"  endDateTime = "2016-03-19T10:02:22.639"  testReferenceID="ID#:FhmJamg0AEmm54Wf1Pzu3A">
			<tr:Extension>
				<ts:TSStepProperties>
					<ts:StepType>Action</ts:StepType>
					<ts:StepGroup>Cleanup</ts:StepGroup>
					<ts:BlockLevel value='0'/>
					<ts:Index value='2'/>
					<ts:TotalTime value='0.0065687'/>
					<ts:ModuleTime value='0.0063918'/>
				</ts:TSStepProperties>
			</tr:Extension>
			<tr:ActionOutcome value = "Done" />
		</tr:SessionAction>
	</tr:ResultSet>
	<tr:TestProgram>
		<c:SerialNumber>
			T450-PC
		</c:SerialNumber>
		<tr:Configuration>
			<c:Collection xsi:type="ts:TS_Collection" flags = "0x0000">
				<c:Item name = "IncludeTSExtensionElements">
					<c:Datum value = "true" xsi:type="ts:TS_boolean" flags = "0x0000"/>
				</c:Item>
				<c:Item name = "IncludeAttributes">
					<c:Datum value = "false" xsi:type="ts:TS_boolean" flags = "0x0000"/>
				</c:Item>
				<c:Item name = "IncludeLimits">
					<c:Datum value = "true" xsi:type="ts:TS_boolean" flags = "0x0000"/>
				</c:Item>
				<c:Item name = "IncludeMeasurements">
					<c:Datum value = "true" xsi:type="ts:TS_boolean" flags = "0x0000"/>
				</c:Item>
				<c:Item name = "IncludeArrayMeasurement">
					<c:Datum value = "2" xsi:type="ts:TS_double" flags = "0x0000"/>
				</c:Item>
				<c:Item name = "ArrayMeasurementFilter">
					<c:Datum value = "3" xsi:type="ts:TS_double" flags = "0x0000"/>
				</c:Item>
				<c:Item name = "ArrayMeasurementMax">
					<c:Datum value = "100" xsi:type="ts:TS_double" flags = "0x0000"/>
				</c:Item>
				<c:Item name = "IncludeTimes">
					<c:Datum value = "true" xsi:type="ts:TS_boolean" flags = "0x0000"/>
				</c:Item>
				<c:Item name = "Format">
					<c:Datum xsi:type="ts:TS_string" flags = "0x0000">
						<c:Value>xml</c:Value>
					</c:Datum>
				</c:Item>
				<c:Item name = "NumericFormat">
					<c:Datum xsi:type="ts:TS_string" flags = "0x0000">
						<c:Value>%$.13g</c:Value>
					</c:Datum>
				</c:Item>
				<c:Item name = "ResultFilterExpression">
					<c:Datum xsi:type="ts:TS_string" flags = "0x0000">
						<c:Value>True</c:Value>
					</c:Datum>
				</c:Item>
				<c:Item name = "GeneratePath">
					<c:Datum value = "true" xsi:type="ts:TS_boolean" flags = "0x0000"/>
				</c:Item>
				<c:Item name = "UseTemporaryFile">
					<c:Datum value = "false" xsi:type="ts:TS_boolean" flags = "0x0000"/>
				</c:Item>
				<c:Item name = "UseSequenceFileNameAsPrefix">
					<c:Datum value = "true" xsi:type="ts:TS_boolean" flags = "0x0000"/>
				</c:Item>
				<c:Item name = "AddTimeAndDateToFileName">
					<c:Datum value = "true" xsi:type="ts:TS_boolean" flags = "0x0000"/>
				</c:Item>
				<c:Item name = "NewFileNameForEachUUT">
					<c:Datum value = "true" xsi:type="ts:TS_boolean" flags = "0x0000"/>
				</c:Item>
				<c:Item name = "ForceFileNameToBeUnique">
					<c:Datum value = "true" xsi:type="ts:TS_boolean" flags = "0x0000"/>
				</c:Item>
				<c:Item name = "AppendToFileIfItExists">
					<c:Datum value = "false" xsi:type="ts:TS_boolean" flags = "0x0000"/>
				</c:Item>
				<c:Item name = "DirectoryType">
					<c:Datum xsi:type="ts:TS_string" flags = "0x0000">
						<c:Value>SpecificDirectory</c:Value>
					</c:Datum>
				</c:Item>
				<c:Item name = "Directory">
					<c:Datum xsi:type="ts:TS_string" flags = "0x0000">
						<c:Value>F:\Bluewave New Energy\SVN_Work\AutoTest_TestStand\trunk\AutoTest_TestStand\Report</c:Value>
					</c:Datum>
				</c:Item>
				<c:Item name = "BaseName">
					<c:Datum xsi:type="ts:TS_string" flags = "0x0000">
						<c:Value>Report</c:Value>
					</c:Datum>
				</c:Item>
				<c:Item name = "UseFormatForExtension">
					<c:Datum value = "true" xsi:type="ts:TS_boolean" flags = "0x0000"/>
				</c:Item>
				<c:Item name = "Extension">
					<c:Datum xsi:type="ts:TS_string" flags = "0x0000">
						<c:Value></c:Value>
					</c:Datum>
				</c:Item>
				<c:Item name = "ReportFilePath">
					<c:Datum xsi:type="ts:TS_string" flags = "0x0000">
						<c:Value></c:Value>
					</c:Datum>
				</c:Item>
				<c:Item name = "DisableReportGeneration">
					<c:Datum value = "false" xsi:type="ts:TS_boolean" flags = "0x0000"/>
				</c:Item>
				<c:Item name = "IncludeStepResults">
					<c:Datum value = "true" xsi:type="ts:TS_boolean" flags = "0x0000"/>
				</c:Item>
				<c:Item name = "BodyGenerator">
					<c:Datum xsi:type="ts:TS_string" flags = "0x0000">
						<c:Value>DLL</c:Value>
					</c:Datum>
				</c:Item>
				<c:Item name = "Colors">
					<c:Collection xsi:type="ts:TS_Collection" flags = "0x0000">
						<c:Item name = "LabelBg">
							<c:Datum xsi:type="ts:TS_string" flags = "0x0000">
								<c:Value>#FFFFFF</c:Value>
							</c:Datum>
						</c:Item>
						<c:Item name = "ValueBg">
							<c:Datum xsi:type="ts:TS_string" flags = "0x0000">
								<c:Value>#32FFFF</c:Value>
							</c:Datum>
						</c:Item>
						<c:Item name = "UUTSeparator">
							<c:Datum xsi:type="ts:TS_string" flags = "0x0000">
								<c:Value>#0000E0</c:Value>
							</c:Datum>
						</c:Item>
						<c:Item name = "HeaderSeparator">
							<c:Datum xsi:type="ts:TS_string" flags = "0x0000">
								<c:Value>#8000CC</c:Value>
							</c:Datum>
						</c:Item>
						<c:Item name = "TableBorder">
							<c:Datum xsi:type="ts:TS_string" flags = "0x0000">
								<c:Value>#000000</c:Value>
							</c:Datum>
						</c:Item>
						<c:Item name = "MainBg">
							<c:Datum xsi:type="ts:TS_string" flags = "0x0000">
								<c:Value>#00C4C4</c:Value>
							</c:Datum>
						</c:Item>
						<c:Item name = "SetupBg">
							<c:Datum xsi:type="ts:TS_string" flags = "0x0000">
								<c:Value>#FF8000</c:Value>
							</c:Datum>
						</c:Item>
						<c:Item name = "CleanupBg">
							<c:Datum xsi:type="ts:TS_string" flags = "0x0000">
								<c:Value>#ADD8E6</c:Value>
							</c:Datum>
						</c:Item>
						<c:Item name = "ReportTextBg">
							<c:Datum xsi:type="ts:TS_string" flags = "0x0000">
								<c:Value>#FF32CC</c:Value>
							</c:Datum>
						</c:Item>
						<c:Item name = "Terminated">
							<c:Datum xsi:type="ts:TS_string" flags = "0x0000">
								<c:Value>#000080</c:Value>
							</c:Datum>
						</c:Item>
						<c:Item name = "Failed">
							<c:Datum xsi:type="ts:TS_string" flags = "0x0000">
								<c:Value>#FF0000</c:Value>
							</c:Datum>
						</c:Item>
						<c:Item name = "Error">
							<c:Datum xsi:type="ts:TS_string" flags = "0x0000">
								<c:Value>#FF0000</c:Value>
							</c:Datum>
						</c:Item>
						<c:Item name = "Passed">
							<c:Datum xsi:type="ts:TS_string" flags = "0x0000">
								<c:Value>#008000</c:Value>
							</c:Datum>
						</c:Item>
						<c:Item name = "Skipped">
							<c:Datum xsi:type="ts:TS_string" flags = "0x0000">
								<c:Value>#B98028</c:Value>
							</c:Datum>
						</c:Item>
						<c:Item name = "Done">
							<c:Datum xsi:type="ts:TS_string" flags = "0x0000">
								<c:Value>#008000</c:Value>
							</c:Datum>
						</c:Item>
						<c:Item name = "Running">
							<c:Datum xsi:type="ts:TS_string" flags = "0x0000">
								<c:Value>#FFCC33</c:Value>
							</c:Datum>
						</c:Item>
						<c:Item name = "TerminatedBg">
							<c:Datum xsi:type="ts:TS_string" flags = "0x0000">
								<c:Value>#0000FF</c:Value>
							</c:Datum>
						</c:Item>
						<c:Item name = "FailedBg">
							<c:Datum xsi:type="ts:TS_string" flags = "0x0000">
								<c:Value>#FF0000</c:Value>
							</c:Datum>
						</c:Item>
						<c:Item name = "ErrorBg">
							<c:Datum xsi:type="ts:TS_string" flags = "0x0000">
								<c:Value>#FF0000</c:Value>
							</c:Datum>
						</c:Item>
						<c:Item name = "PassedBg">
							<c:Datum xsi:type="ts:TS_string" flags = "0x0000">
								<c:Value>#00FF00</c:Value>
							</c:Datum>
						</c:Item>
						<c:Item name = "SkippedBg">
							<c:Datum xsi:type="ts:TS_string" flags = "0x0000">
								<c:Value>#FFFF00</c:Value>
							</c:Datum>
						</c:Item>
						<c:Item name = "DoneBg">
							<c:Datum xsi:type="ts:TS_string" flags = "0x0000">
								<c:Value>#00FFCC</c:Value>
							</c:Datum>
						</c:Item>
						<c:Item name = "RunningBg">
							<c:Datum xsi:type="ts:TS_string" flags = "0x0000">
								<c:Value>#FFCC33</c:Value>
							</c:Datum>
						</c:Item>
						<c:Item name = "FailureStackLabelBg">
							<c:Datum xsi:type="ts:TS_string" flags = "0x0000">
								<c:Value>#FF2020</c:Value>
							</c:Datum>
						</c:Item>
						<c:Item name = "FailureStackValueBg">
							<c:Datum xsi:type="ts:TS_string" flags = "0x0000">
								<c:Value>#D0D0D0</c:Value>
							</c:Datum>
						</c:Item>
						<c:Item name = "BatchHeadingBg">
							<c:Datum xsi:type="ts:TS_string" flags = "0x0000">
								<c:Value>#00C4C4</c:Value>
							</c:Datum>
						</c:Item>
					</c:Collection>
				</c:Item>
				<c:Item name = "DateAndTimeFormat">
					<c:Datum xsi:type="ts:TS_string" flags = "0x0000">
						<c:Value>DateFirst</c:Value>
					</c:Datum>
				</c:Item>
				<c:Item name = "NewFileNameForEachBatch">
					<c:Datum value = "false" xsi:type="ts:TS_boolean" flags = "0x0000"/>
				</c:Item>
				<c:Item name = "NewBatchFileNameForEachBatch">
					<c:Datum value = "false" xsi:type="ts:TS_boolean" flags = "0x0000"/>
				</c:Item>
				<c:Item name = "NewFileNameForEachTestSocket">
					<c:Datum value = "false" xsi:type="ts:TS_boolean" flags = "0x0000"/>
				</c:Item>
				<c:Item name = "StoreUUTReportWithBatchReport">
					<c:Datum value = "true" xsi:type="ts:TS_boolean" flags = "0x0000"/>
				</c:Item>
				<c:Item name = "BatchBaseName">
					<c:Datum xsi:type="ts:TS_string" flags = "0x0000">
						<c:Value>BatchReport</c:Value>
					</c:Datum>
				</c:Item>
				<c:Item name = "LabelSize">
					<c:Datum value = "26" xsi:type="ts:TS_double" flags = "0x0000"/>
				</c:Item>
				<c:Item name = "RelStylesheetPath">
					<c:Datum xsi:type="ts:TS_string" flags = "0x0000">
						<c:Value>tr5_horizontal.xsl</c:Value>
					</c:Datum>
				</c:Item>
				<c:Item name = "StylesheetPath">
					<c:Datum xsi:type="ts:TS_string" flags = "0x0000">
						<c:Value>D:\Program Files\National Instruments\TestStand 2014\Components\Models\TestStandModels\ATML\StyleSheets\tr5_horizontal.xsl</c:Value>
					</c:Datum>
				</c:Item>
				<c:Item name = "StylesheetMRU">
					<c:IndexedArray dimensions="[5]" lowerBounds="[0]" upperBounds="[4]" xsi:type="ts:TS_stringArray" flags = "0x0000">
						<ts:Element position ="[0]">
							<c:Value>horizontal.xsl</c:Value>
						</ts:Element>
						<ts:Element position ="[1]">
							<c:Value>report.xsl</c:Value>
						</ts:Element>
						<ts:Element position ="[2]">
							<c:Value>expand.xsl</c:Value>
						</ts:Element>
						<ts:Element position ="[3]">
							<c:Value></c:Value>
						</ts:Element>
						<ts:Element position ="[4]">
							<c:Value></c:Value>
						</ts:Element>
					</c:IndexedArray>
				</c:Item>
				<c:Item name = "ATMLStylesheetMRU">
					<c:IndexedArray dimensions="[3]" lowerBounds="[0]" upperBounds="[2]" xsi:type="ts:TS_stringArray" flags = "0x0000">
						<ts:Element position ="[0]">
							<c:Value>TR_horizontal.xsl</c:Value>
						</ts:Element>
						<ts:Element position ="[1]">
							<c:Value>trml.xsl</c:Value>
						</ts:Element>
						<ts:Element position ="[2]">
							<c:Value></c:Value>
						</ts:Element>
					</c:IndexedArray>
				</c:Item>
				<c:Item name = "StoreStylesheetAbsolutePath">
					<c:Datum value = "true" xsi:type="ts:TS_boolean" flags = "0x0000"/>
				</c:Item>
				<c:Item name = "ProcessOnTheFly">
					<c:Datum value = "false" xsi:type="ts:TS_boolean" flags = "0x0000"/>
				</c:Item>
				<c:Item name = "PurgeOnTheFlyResults">
					<c:Datum value = "false" xsi:type="ts:TS_boolean" flags = "0x0000"/>
				</c:Item>
				<c:Item name = "IncludeStepResultComments">
					<c:Datum value = "true" xsi:type="ts:TS_boolean" flags = "0x0000"/>
				</c:Item>
				<c:Item name = "UseLocalizedDecimalPoint">
					<c:Datum value = "false" xsi:type="ts:TS_boolean" flags = "0x0000"/>
				</c:Item>
				<c:Item name = "ReportStyle">
					<c:Datum xsi:type="ts:TS_string" flags = "0x0000">
						<c:Value>ATML5</c:Value>
					</c:Datum>
				</c:Item>
				<c:Item name = "ReportFileSequentialModelExpression">
					<c:Datum xsi:type="ts:TS_string" flags = "0x0000">
						<c:Value>"$(ClientFileDir)\\$(ClientFileName)_Report[$(FileTime)][$(FileDate)]$(Unique).$(FileExtension)"</c:Value>
					</c:Datum>
				</c:Item>
				<c:Item name = "ReportFileParallelModelExpression">
					<c:Datum xsi:type="ts:TS_string" flags = "0x0000">
						<c:Value>"$(ClientFileDir)\\$(ClientFileName)_Report[$(FileTime)][$(FileDate)]$(Unique).$(FileExtension)"</c:Value>
					</c:Datum>
				</c:Item>
				<c:Item name = "ReportFileBatchModelExpression">
					<c:Datum xsi:type="ts:TS_string" flags = "0x0000">
						<c:Value>"$(ClientFileDir)\\$(ClientFileName)_BatchReport[$(FileTime)][$(FileDate)]$(Unique).$(FileExtension)"</c:Value>
					</c:Datum>
				</c:Item>
				<c:Item name = "BatchFileBatchModelExpression">
					<c:Datum xsi:type="ts:TS_string" flags = "0x0000">
						<c:Value>"$(ClientFileDir)\\$(ClientFileName)_BatchReport[$(FileTime)][$(FileDate)]$(Unique).$(FileExtension)"</c:Value>
					</c:Datum>
				</c:Item>
				<c:Item name = "NewFileNameForEachUUTStatus">
					<c:Datum value = "false" xsi:type="ts:TS_boolean" flags = "0x0000"/>
				</c:Item>
				<c:Item name = "ReportPathMacroListString">
					<c:Datum xsi:type="ts:TS_string" flags = "0x0000">
						<c:Value></c:Value>
					</c:Datum>
				</c:Item>
				<c:Item name = "BatchReportPathMacroListString">
					<c:Datum xsi:type="ts:TS_string" flags = "0x0000">
						<c:Value></c:Value>
					</c:Datum>
				</c:Item>
				<c:Item name = "CheckIfMacroListIsUnchanged">
					<c:Datum value = "true" xsi:type="ts:TS_boolean" flags = "0x0000"/>
				</c:Item>
				<c:Item name = "ATML5StylesheetMRU">
					<c:IndexedArray dimensions="[3]" lowerBounds="[0]" upperBounds="[2]" xsi:type="ts:TS_stringArray" flags = "0x0000">
						<ts:Element position ="[0]">
							<c:Value>tr5_horizontal.xsl</c:Value>
						</ts:Element>
						<ts:Element position ="[1]">
							<c:Value>tr5_report.xsl</c:Value>
						</ts:Element>
						<ts:Element position ="[2]">
							<c:Value>tr5_expand.xsl</c:Value>
						</ts:Element>
					</c:IndexedArray>
				</c:Item>
				<c:Item name = "Atml_Rpt_Options">
					<c:Collection xsi:type="ts:TS_Collection" flags = "0x0000">
						<c:Item name = "AddReportText">
							<c:Datum value = "true" xsi:type="ts:TS_boolean" flags = "0x0000"/>
						</c:Item>
						<c:Item name = "ExtensionDLLAbsolutePath">
							<c:Datum xsi:type="ts:TS_string" flags = "0x0000">
								<c:Value></c:Value>
							</c:Datum>
						</c:Item>
						<c:Item name = "TestResultsSchemaPath">
							<c:Datum xsi:type="ts:TS_string" flags = "0x0000">
								<c:Value></c:Value>
							</c:Datum>
						</c:Item>
					</c:Collection>
				</c:Item>
				<c:Item name = "ATML6StylesheetMRU">
					<c:IndexedArray dimensions="[5]" lowerBounds="[0]" upperBounds="[4]" xsi:type="ts:TS_stringArray" flags = "0x0000">
						<ts:Element position ="[0]">
							<c:Value>tr6_horizontal.xsl</c:Value>
						</ts:Element>
						<ts:Element position ="[1]">
							<c:Value>tr6_report.xsl</c:Value>
						</ts:Element>
						<ts:Element position ="[2]">
							<c:Value>tr6_expand.xsl</c:Value>
						</ts:Element>
						<ts:Element position ="[3]">
							<c:Value></c:Value>
						</ts:Element>
						<ts:Element position ="[4]">
							<c:Value></c:Value>
						</ts:Element>
					</c:IndexedArray>
				</c:Item>
			</c:Collection>
		</tr:Configuration>
	</tr:TestProgram>
	<tr:TestStation>
		<c:SerialNumber>T450-PC</c:SerialNumber>
	</tr:TestStation>
	<tr:UUT>
		<c:SerialNumber>NONE</c:SerialNumber>
	</tr:UUT>
	<tr:Extension>
		<ts:TSResultSetProperties>
			<ts:NumOfResults value = '44'/>
		</ts:TSResultSetProperties>
	</tr:Extension>
</trc:TestResults>
</trc:TestResultsCollection>
